openfisca_france_data/__init__.py
openfisca_france_data/aggregates.py
openfisca_france_data/base_survey.py
openfisca_france_data/common.py
openfisca_france_data/comparator.py
openfisca_france_data/config.py
openfisca_france_data/smic.py
openfisca_france_data/surveys.py
openfisca_france_data/utils.py
openfisca_france_data/assets/__init__.py
openfisca_france_data/assets/aggregats/france_entiere/france_entiere_2019.json
openfisca_france_data/assets/aggregats/france_entiere/france_entiere_2020.json
openfisca_france_data/assets/aggregats/france_entiere/france_entiere_2021.json
openfisca_france_data/assets/aggregats/france_entiere/france_entiere_2022.json
openfisca_france_data/assets/aggregats/france_entiere/france_entiere_2023.json
openfisca_france_data/assets/aggregats/france_entiere/france_entiere_template.json
openfisca_france_data/assets/aggregats/ines/ines_2019.json
openfisca_france_data/assets/aggregats/ines/ines_2020.json
openfisca_france_data/assets/aggregats/taxipp/agregats_tests_taxipp_2_0.xlsx
openfisca_france_data/assets/zone_apl_data/__init__.py
openfisca_france_data/assets/zone_apl_data/codeAplReader.py
openfisca_france_data/assets/zone_apl_data/zone_apl/__init__.py
openfisca_france_data/assets/zone_apl_data/zone_apl/zone_apl_imputation_data_reader.py
openfisca_france_data/dads/input_data_builder/__init__.py
openfisca_france_data/dads/input_data_builder/create_variables_individuelles.py
openfisca_france_data/erfs/__init__.py
openfisca_france_data/erfs/scenario.py
openfisca_france_data/erfs/input_data_builder/__init__.py
openfisca_france_data/erfs/input_data_builder/base.py
openfisca_france_data/erfs/input_data_builder/run_all.py
openfisca_france_data/erfs/input_data_builder/step_01_pre_processing.py
openfisca_france_data/erfs/input_data_builder/step_02_imputation_loyer.py
openfisca_france_data/erfs/input_data_builder/step_03_fip.py
openfisca_france_data/erfs/input_data_builder/step_04_famille.py
openfisca_france_data-3.8.0.dist-info/licenses/LICENSE
openfisca_france_data-3.8.0.dist-info/METADATA
openfisca_france_data-3.8.0.dist-info/WHEEL
openfisca_france_data-3.8.0.dist-info/entry_points.txt
openfisca_france_data-3.8.0.dist-info/top_level.txt
openfisca_france_data-3.8.0.dist-info/RECORD
