Metadata-Version: 2.4
Name: OpenFisca-France-Data
Version: 3.8.0
Summary: OpenFisca-France-Data module to work with French survey data
Home-page: https://github.com/openfisca/openfisca-france-data
Author: OpenFisca Team
Author-email: contact@openfisca.fr
License: http://www.fsf.org/licensing/licenses/agpl-3.0.html
Keywords: tax benefit social survey data microsimulation
Classifier: Development Status :: 2 - Pre-Alpha
Classifier: License :: OSI Approved :: GNU Affero General Public License v3
Classifier: Operating System :: POSIX
Classifier: Programming Language :: Python
Classifier: Programming Language :: Python :: 3.10
Classifier: Programming Language :: Python :: 3.11
Classifier: Programming Language :: Python :: 3.12
Classifier: Programming Language :: Python :: 3.13
Classifier: Topic :: Scientific/Engineering :: Information Analysis
Requires-Python: >=3.10
License-File: LICENSE
Requires-Dist: multipledispatch<1.0.0,>=0.6.0
Requires-Dist: OpenFisca-France<176.0.0,>=175.0.0
Requires-Dist: OpenFisca-survey-manager<4.0.0,>=3.0.0
Provides-Extra: test
Requires-Dist: click<9.0.0,>=8.0.0; extra == "test"
Requires-Dist: autopep8<3,>=2.0.2; extra == "test"
Requires-Dist: bumpver>=2022.1120; extra == "test"
Requires-Dist: dtale; extra == "test"
Requires-Dist: flake8<7.0.0,>=6.0.0; extra == "test"
Requires-Dist: ipdb<1.0,>=0.13; extra == "test"
Requires-Dist: ipython<8.0.0,>=7.5.0; extra == "test"
Requires-Dist: mypy<1.0.0,>=0.670; extra == "test"
Requires-Dist: pypandoc; extra == "test"
Requires-Dist: scipy<2.0.0,>=1.2.1; extra == "test"
Requires-Dist: toolz<1.0.0,>=0.9.0; extra == "test"
Dynamic: author
Dynamic: author-email
Dynamic: classifier
Dynamic: description
Dynamic: description-content-type
Dynamic: home-page
Dynamic: keywords
Dynamic: license
Dynamic: license-file
Dynamic: provides-extra
Dynamic: requires-dist
Dynamic: requires-python
Dynamic: summary
